cliprec/__init__.py
cliprec/__main__.py
cliprec-1.0.2.dist-info/LICENSE
cliprec-1.0.2.dist-info/METADATA
cliprec-1.0.2.dist-info/WHEEL
cliprec-1.0.2.dist-info/top_level.txt
cliprec-1.0.2.dist-info/RECORD
