Metadata-Version: 2.1
Name: cliprec
Version: 1.0.2
Summary: A cross-platform clipboard monitoring and recording tool. Uses pyperclip. Only works for text.
Author-email: Al Sweigart <al@inventwithpython.com>
License: GNU GENERAL PUBLIC LICENSE
Project-URL: Homepage, https://github.com/asweigart/cliprec
Project-URL: Bug Tracker, https://github.com/asweigart/cliprec/issues
Keywords: clipboard
Classifier: Development Status :: 5 - Production/Stable
Classifier: Environment :: Win32 (MS Windows)
Classifier: Environment :: X11 Applications
Classifier: Environment :: MacOS X
Classifier: Intended Audience :: Developers
Classifier: Operating System :: OS Independent
Classifier: License :: OSI Approved :: MIT License
Classifier: Programming Language :: Python
Classifier: Programming Language :: Python :: 2
Classifier: Programming Language :: Python :: 3
Requires-Python: >=2.7
License-File: LICENSE
Requires-Dist: pyperclip
